{
  "slug": "wormhole",
  "name": "Wormhole",
  "description": "Generic cross-chain message passing protocol connecting multiple blockchains",
  "category": "Bridge",
  "logo_url": "https://images.ctfassets.net/t3wqy70tc3bv/zjpjBpSpX6wiIdgfoLeKc/b7c1a836bbc7a4a850623ddee15f3158/wormhole-logo-full-color-rgb-2000px_72ppi__1_.png",
  "chains": [
    "ethereum",
    "solana",
    "bsc",
    "polygon",
    "arbitrum",
    "optimism",
    "base"
  ],
  "bounty": {
    "max": 5000000,
    "min": 1000,
    "kyc_required": true,
    "payout_token": "USDC"
  },
  "severity_payouts": {
    "critical": {
      "min": 1000000,
      "max": 5000000,
      "description": "Direct theft of user funds or cross-chain exploit"
    },
    "high": {
      "min": 100000,
      "max": 500000,
      "description": "Temporary freezing of funds or guardian manipulation"
    },
    "medium": {
      "min": 10000,
      "max": 100000,
      "description": "Protocol disruption or message spoofing"
    },
    "low": {
      "min": 1000,
      "max": 10000,
      "description": "Informational findings"
    }
  },
  "source": "whiteclaws",
  "contracts": [
    {
      "address": "0x98f3c9e6E3fAce36bAAd05FE09d375Ef1464288B",
      "network": "ethereum",
      "name": "Wormhole Core Bridge",
      "type": "Core"
    }
  ],
  "scope": {
    "in_scope": [
      "Core bridge contracts",
      "Guardian verification",
      "Token bridge",
      "VAA parsing and validation"
    ],
    "out_of_scope": [
      "Frontend portal",
      "Off-chain guardian nodes",
      "Third-party relayers"
    ],
    "functions_critical": [
      "publishMessage",
      "parseAndVerifyVM",
      "completeTransfer"
    ],
    "functions_high": [
      "submitContractUpgrade",
      "registerChain",
      "updateGuardianSet"
    ]
  },
  "updated_at": "2025-07-21T07:21:20.279Z",
  "live_since": "2022-02-11T15:00:00.000Z",
  "poc_required": true,
  "program_tags": [
    "Verified Program",
    "KYC Required",
    "PoC Required"
  ],
  "program_rules": [
    "Proof of Concept is required for all submissions. Reports without a working PoC demonstrating the vulnerability will not be considered.",
    "KYC verification is required before bounty payout. Researchers must complete identity verification to receive rewards.",
    "Only previously unreported vulnerabilities are eligible. Duplicate submissions will be closed.",
    "Vulnerabilities must be reported through the WhiteClaws platform. Public disclosure before resolution disqualifies the submission.",
    "Testing must not disrupt live protocol operations. Use mainnet forks or testnets for Proof of Concept execution.",
    "For Critical severity findings, the security team may arrange direct communication for expedited resolution."
  ],
  "submission_requirements": {
    "report_format": [
      "Descriptive title with severity classification",
      "Detailed vulnerability description including affected functions",
      "Step-by-step reproduction instructions",
      "Proof of Concept (code or transaction simulation)",
      "Impact analysis with realistic attack scenario",
      "Suggested fix or mitigation"
    ],
    "severity_criteria": {
      "critical": "Direct loss of funds, protocol insolvency, or permanent freezing of funds exceeding $1M",
      "high": "Temporary freezing of funds, manipulation of protocol parameters, or theft below critical threshold",
      "medium": "Griefing attacks, gas optimization issues with material impact, or accounting discrepancies",
      "low": "Informational findings, best practice violations, or low-impact edge cases"
    }
  },
  "eligibility": [
    "KYC verification required before payout",
    "Proof of Concept demonstrating exploitability is mandatory",
    "Submissions from current or former employees/contractors of the protocol team are not eligible",
    "Findings must be original work — no re-submission of known issues"
  ],
  "audits": [
    {
      "id": "wormhole-trail-of-bits-2023-03",
      "title": "2023-03-wormhole-securityreview.pdf",
      "auditor": "Trail of Bits",
      "date": "2023-03",
      "pdf_url": "https://raw.githubusercontent.com/trailofbits/publications/master/reviews/2023-03-wormhole-securityreview.pdf"
    },
    {
      "id": "wormhole-cyfrin-2024-01",
      "title": "2024-01-10-cyfrin-wormhole-thermae-v2.1.pdf",
      "auditor": "Cyfrin",
      "date": "2024-01",
      "pdf_url": "https://raw.githubusercontent.com/Cyfrin/cyfrin-audit-reports/main/reports/2024-01-10-cyfrin-wormhole-thermae-v2.1.pdf"
    },
    {
      "id": "wormhole-cyfrin-2024-04",
      "title": "2024-04-11-cyfrin-wormhole-evm-ntt-v2.pdf",
      "auditor": "Cyfrin",
      "date": "2024-04",
      "pdf_url": "https://raw.githubusercontent.com/Cyfrin/cyfrin-audit-reports/main/reports/2024-04-11-cyfrin-wormhole-evm-ntt-v2.pdf"
    },
    {
      "id": "wormhole-cyfrin-2024-07",
      "title": "2024-07-23-cyfrin-wormhole-NTT-Diff-v1.0.pdf",
      "auditor": "Cyfrin",
      "date": "2024-07",
      "pdf_url": "https://raw.githubusercontent.com/Cyfrin/cyfrin-audit-reports/main/reports/2024-07-23-cyfrin-wormhole-NTT-Diff-v1.0.pdf"
    },
    {
      "id": "wormhole-cyfrin-2024-10",
      "title": "2024-10-04-cyfrin-wormhole-multigov-v2.0.pdf",
      "auditor": "Cyfrin",
      "date": "2024-10",
      "pdf_url": "https://raw.githubusercontent.com/Cyfrin/cyfrin-audit-reports/main/reports/2024-10-04-cyfrin-wormhole-multigov-v2.0.pdf"
    },
    {
      "id": "wormhole-cyfrin-2026-02",
      "title": "2026-02-10-cyfrin-securitize-bridge-wormhole-executor-v2.0.pdf",
      "auditor": "Cyfrin",
      "date": "2026-02",
      "pdf_url": "https://raw.githubusercontent.com/Cyfrin/cyfrin-audit-reports/main/reports/2026-02-10-cyfrin-securitize-bridge-wormhole-executor-v2.0.pdf"
    }
  ],
  "audit_count": 6,
  "last_audited": "2026-02",
  "auditors": [
    "Cyfrin",
    "Trail of Bits"
  ]
}
